javiche/__init__.py
javiche/_modidx.py
javiche/invdes.py
javiche/jaxify.py
javiche-0.0.6.dist-info/LICENSE
javiche-0.0.6.dist-info/METADATA
javiche-0.0.6.dist-info/WHEEL
javiche-0.0.6.dist-info/entry_points.txt
javiche-0.0.6.dist-info/top_level.txt
javiche-0.0.6.dist-info/RECORD
