Metadata-Version: 2.1
Name: javiche
Version: 0.0.6
Summary: A JAX wrapper around ceviche to make interoperability easier. In the future it might make sense to update ceviche itself to use JAX internally.
Home-page: https://github.com/Jan-David-Black/javiche
Author: Jan David Fischbach
Author-email: jan-david.fischbach@blacksemicon.de
License: Apache Software License 2.0
Keywords: nbdev jupyter notebook python ceviche fdtd inverse-design
Classifier: Development Status :: 4 - Beta
Classifier: Intended Audience :: Developers
Classifier: Natural Language :: English
Classifier: Programming Language :: Python :: 3.7
Classifier: Programming Language :: Python :: 3.8
Classifier: Programming Language :: Python :: 3.9
Classifier: Programming Language :: Python :: 3.10
Classifier: License :: OSI Approved :: Apache Software License
Requires-Python: >=3.7
License-File: LICENSE
Requires-Dist: numpy
Requires-Dist: ceviche
Requires-Dist: jax
Requires-Dist: jaxlib
Provides-Extra: dev
Requires-Dist: nbdev (>=2.3) ; extra == 'dev'
Requires-Dist: tqdm ; extra == 'dev'
Requires-Dist: jupyter ; extra == 'dev'
Requires-Dist: ipywidgets ; extra == 'dev'
